README.rst
setup.py
django_simplify.egg-info/PKG-INFO
django_simplify.egg-info/SOURCES.txt
django_simplify.egg-info/dependency_links.txt
django_simplify.egg-info/not-zip-safe
django_simplify.egg-info/requires.txt
django_simplify.egg-info/top_level.txt
simplify/__about__.py
simplify/__init__.py
simplify/apps.py
simplify/simplify.py
simplify/utils.py
simplify/management/__init__.py
simplify/management/_command_functions.py
simplify/management/_helper.py
simplify/management/_messages.py
simplify/management/commands/__init__.py
simplify/management/commands/create_app.py
simplify/management/commands/create_model.py
simplify/management/commands/create_view.py