Metadata-Version: 2.1
Name: django-simplify
Version: 0.2
Summary: Provides Ruby on Rails-like command line functionalities, models and helper functions so you can focus on development and removes the pain of repeating frequent actions.
Home-page: https://github.com/tushortz/django-simplify
Author: Taiwo Kareem
Author-email: taiwo.kareem36@gmail.com
License: BSD
Keywords: django,model helpers,django commands,helpers
Platform: UNKNOWN
Classifier: Development Status :: 3 - Alpha
Classifier: Environment :: Web Environment
Classifier: Intended Audience :: Developers
Classifier: License :: OSI Approved :: BSD License
Classifier: Natural Language :: English
Classifier: Programming Language :: Python :: 3.6
Classifier: Programming Language :: Python :: 3.7
Classifier: Programming Language :: Python :: 3.8
Classifier: Framework :: Django
Classifier: Operating System :: OS Independent
Classifier: Topic :: Software Development :: Libraries :: Application Frameworks
Classifier: Topic :: Software Development :: Libraries :: Python Modules
Provides-Extra: docs
